{
  "metadata": [
    {
      "TableName": "Category",
      "ColumnName": "Name",
      "AllowedValues": null,
      "Regex": null,
      "DataType": "nvarchar (2000)",
      "IsRequired": null
    },
    {
      "TableName": "Category",
      "ColumnName": "Description",
      "AllowedValues": null,
      "Regex": null,
      "DataType": "nvarchar (max)",
      "IsRequired": null
    },
    {
      "TableName": "Category",
      "ColumnName": "Id",
      "AllowedValues": null,
      "Regex": null,
      "DataType": "uniqueidentifier",
      "IsRequired": null
    },
    {
      "TableName": "UserProfile",
      "ColumnName": "UserName",
      "AllowedValues": null,
      "Regex": null,
      "DataType": "nvarchar (3999)",
      "IsRequired": null
    },
    {
      "TableName": "UserProfile",
      "ColumnName": "FirstName",
      "AllowedValues": null,
      "Regex": null,
      "DataType": "nvarchar (2000)",
      "IsRequired": null
    },
    {
      "TableName": "UserProfile",
      "ColumnName": "LastName",
      "AllowedValues": null,
      "Regex": null,
      "DataType": "nvarchar (2000)",
      "IsRequired": null
    },
    {
      "TableName": "UserProfile",
      "ColumnName": "ProfileImage",
      "AllowedValues": null,
      "Regex": null,
      "DataType": "nvarchar (4000)",
      "IsRequired": null
    },
    {
      "TableName": "UserProfile",
      "ColumnName": "Id",
      "AllowedValues": null,
      "Regex": null,
      "DataType": "uniqueidentifier",
      "IsRequired": null
    },
    {
      "TableName": "Task",
      "ColumnName": "Title",
      "AllowedValues": null,
      "Regex": null,
      "DataType": "nvarchar (2000)",
      "IsRequired": null
    },
    {
      "TableName": "Task",
      "ColumnName": "Description",
      "AllowedValues": null,
      "Regex": null,
      "DataType": "nvarchar (max)",
      "IsRequired": null
    },
    {
      "TableName": "Task",
      "ColumnName": "Location",
      "AllowedValues": null,
      "Regex": null,
      "DataType": "nvarchar (2000)",
      "IsRequired": null
    },
    {
      "TableName": "Task",
      "ColumnName": "Latitude",
      "AllowedValues": null,
      "Regex": null,
      "DataType": "decimal (10, 2)",
      "IsRequired": null
    },
    {
      "TableName": "Task",
      "ColumnName": "Longitude",
      "AllowedValues": null,
      "Regex": null,
      "DataType": "decimal (10, 2)",
      "IsRequired": null
    },
    {
      "TableName": "Task",
      "ColumnName": "TimeFrom",
      "AllowedValues": null,
      "Regex": null,
      "DataType": "datetime2 (7)",
      "IsRequired": null
    },
    {
      "TableName": "Task",
      "ColumnName": "TimeTo",
      "AllowedValues": null,
      "Regex": null,
      "DataType": "datetime2 (7)",
      "IsRequired": null
    },
    {
      "TableName": "Task",
      "ColumnName": "CreatedAt",
      "AllowedValues": null,
      "Regex": null,
      "DataType": "datetime2 (7)",
      "IsRequired": null
    },
    {
      "TableName": "Task",
      "ColumnName": "CreatedBy",
      "AllowedValues": null,
      "Regex": null,
      "DataType": "nvarchar (3999)",
      "IsRequired": null
    },
    {
      "TableName": "Task",
      "ColumnName": "IsResolved",
      "AllowedValues": null,
      "Regex": null,
      "DataType": "bit",
      "IsRequired": null
    },
    {
      "TableName": "Task",
      "ColumnName": "Id",
      "AllowedValues": null,
      "Regex": null,
      "DataType": "uniqueidentifier",
      "IsRequired": null
    },
    {
      "TableName": "TaskReservation",
      "ColumnName": "ReservedBy",
      "AllowedValues": null,
      "Regex": null,
      "DataType": "nvarchar (3999)",
      "IsRequired": null
    },
    {
      "TableName": "TaskReservation",
      "ColumnName": "ReservedAt",
      "AllowedValues": null,
      "Regex": null,
      "DataType": "datetime2 (7)",
      "IsRequired": null
    },
    {
      "TableName": "TaskReservation",
      "ColumnName": "IsCompleted",
      "AllowedValues": null,
      "Regex": null,
      "DataType": "bit",
      "IsRequired": null
    },
    {
      "TableName": "TaskReservation",
      "ColumnName": "Id",
      "AllowedValues": null,
      "Regex": null,
      "DataType": "uniqueidentifier",
      "IsRequired": null
    },
    {
      "TableName": "UserKarma",
      "ColumnName": "TotalCompleted",
      "AllowedValues": null,
      "Regex": null,
      "DataType": "int",
      "IsRequired": null
    },
    {
      "TableName": "UserKarma",
      "ColumnName": "LastCompletedAt",
      "AllowedValues": null,
      "Regex": null,
      "DataType": "datetime2 (7)",
      "IsRequired": null
    },
    {
      "TableName": "UserKarma",
      "ColumnName": "Id",
      "AllowedValues": null,
      "Regex": null,
      "DataType": "uniqueidentifier",
      "IsRequired": null
    }
  ],
  "entities": [
    {
      "entityKey": "9bb8d9cc-43e0-80a1-2126-07a775d688ca",
      "tableName": "Category",
      "objectName": null,
      "controllerName": "category",
      "softDeleteColumn": null,
      "defaultValue": null,
      "properties": [
        {
          "propertyId": "31b94824-9132-741b-e5e6-f08b457b7ec3",
          "propertyName": "Name",
          "modelPropertyName": null,
          "isKey": false,
          "isReadOnly": false,
          "isRequired": false,
          "defaultValue": null,
          "referencingEntityKey": null,
          "relatedModelPropertyName": null
        },
        {
          "propertyId": "fc7816b6-4e41-66be-abf6-c1cee07aeaa5",
          "propertyName": "Description",
          "modelPropertyName": null,
          "isKey": false,
          "isReadOnly": false,
          "isRequired": false,
          "defaultValue": null,
          "referencingEntityKey": null,
          "relatedModelPropertyName": null
        },
        {
          "propertyId": "00000000-0000-0000-0000-000000000000",
          "propertyName": "Id",
          "modelPropertyName": null,
          "isKey": true,
          "isReadOnly": true,
          "isRequired": null,
          "defaultValue": null,
          "referencingEntityKey": null,
          "relatedModelPropertyName": null
        }
      ],
      "entityRoles": [
        {
          "getOne": true,
          "getAll": true,
          "put": true,
          "post": true,
          "delete": true,
          "editFilter": null,
          "viewFilter": null,
          "roleKey": "anonymous"
        },
        {
          "getOne": true,
          "getAll": true,
          "put": true,
          "post": true,
          "delete": true,
          "editFilter": null,
          "viewFilter": null,
          "roleKey": "user"
        },
        {
          "getOne": true,
          "getAll": true,
          "put": true,
          "post": true,
          "delete": true,
          "editFilter": null,
          "viewFilter": null,
          "roleKey": "admin"
        }
      ],
      "entityRelations": []
    },
    {
      "entityKey": "31099994-b3cc-3ade-768f-8de8d1d47fac",
      "tableName": "UserProfile",
      "objectName": null,
      "controllerName": "profile",
      "softDeleteColumn": null,
      "defaultValue": null,
      "properties": [
        {
          "propertyId": "729cf60f-2a34-68c4-6980-f66dfdaba366",
          "propertyName": "UserName",
          "modelPropertyName": null,
          "isKey": false,
          "isReadOnly": false,
          "isRequired": false,
          "defaultValue": "$user",
          "referencingEntityKey": null,
          "relatedModelPropertyName": null
        },
        {
          "propertyId": "52c85e20-a8a0-ab33-31ee-e9498cb53c7f",
          "propertyName": "FirstName",
          "modelPropertyName": null,
          "isKey": false,
          "isReadOnly": false,
          "isRequired": false,
          "defaultValue": null,
          "referencingEntityKey": null,
          "relatedModelPropertyName": null
        },
        {
          "propertyId": "e3be9aa0-1540-6c0c-7d59-8444ae68e8aa",
          "propertyName": "LastName",
          "modelPropertyName": null,
          "isKey": false,
          "isReadOnly": false,
          "isRequired": false,
          "defaultValue": null,
          "referencingEntityKey": null,
          "relatedModelPropertyName": null
        },
        {
          "propertyId": "66f29b13-a3c8-6ac7-4699-c0fb682c16e2",
          "propertyName": "ProfileImage",
          "modelPropertyName": null,
          "isKey": false,
          "isReadOnly": false,
          "isRequired": false,
          "defaultValue": null,
          "referencingEntityKey": null,
          "relatedModelPropertyName": null
        },
        {
          "propertyId": "00000000-0000-0000-0000-000000000000",
          "propertyName": "Id",
          "modelPropertyName": null,
          "isKey": true,
          "isReadOnly": true,
          "isRequired": null,
          "defaultValue": null,
          "referencingEntityKey": null,
          "relatedModelPropertyName": null
        }
      ],
      "entityRoles": [
        {
          "getOne": true,
          "getAll": true,
          "put": true,
          "post": true,
          "delete": true,
          "editFilter": "{\u0022conjunction\u0022:\u0022and\u0022,\u0022comparisons\u0022:[{\u0022operator\u0022:\u0022eq\u0022,\u0022property\u0022:\u0022userName\u0022,\u0022filter\u0022:\u0022$user\u0022}],\u0022operator\u0022:\u0022eq\u0022}",
          "viewFilter": "{\u0022conjunction\u0022:\u0022and\u0022,\u0022comparisons\u0022:[{\u0022operator\u0022:\u0022eq\u0022,\u0022property\u0022:\u0022userName\u0022,\u0022filter\u0022:\u0022$user\u0022}],\u0022operator\u0022:\u0022eq\u0022}",
          "roleKey": "user"
        },
        {
          "getOne": true,
          "getAll": true,
          "put": true,
          "post": true,
          "delete": true,
          "editFilter": null,
          "viewFilter": null,
          "roleKey": "admin"
        },
        {
          "getOne": true,
          "getAll": true,
          "put": false,
          "post": false,
          "delete": false,
          "editFilter": null,
          "viewFilter": null,
          "roleKey": "anonymous"
        }
      ],
      "entityRelations": []
    },
    {
      "entityKey": "f284bf21-df3d-56c7-573c-a3424169917e",
      "tableName": "Task",
      "objectName": null,
      "controllerName": "task",
      "softDeleteColumn": null,
      "defaultValue": null,
      "properties": [
        {
          "propertyId": "475b885a-f852-b160-0d53-f1bf500bff8b",
          "propertyName": "Title",
          "modelPropertyName": null,
          "isKey": false,
          "isReadOnly": false,
          "isRequired": false,
          "defaultValue": null,
          "referencingEntityKey": null,
          "relatedModelPropertyName": null
        },
        {
          "propertyId": "e574391e-cf73-5038-3b95-df266d55a192",
          "propertyName": "Description",
          "modelPropertyName": null,
          "isKey": false,
          "isReadOnly": false,
          "isRequired": false,
          "defaultValue": null,
          "referencingEntityKey": null,
          "relatedModelPropertyName": null
        },
        {
          "propertyId": "01f80b79-f414-4104-dd5f-151f9f8c0e1a",
          "propertyName": "Category",
          "modelPropertyName": null,
          "isKey": false,
          "isReadOnly": false,
          "isRequired": false,
          "defaultValue": null,
          "referencingEntityKey": "9bb8d9cc-43e0-80a1-2126-07a775d688ca",
          "relatedModelPropertyName": null
        },
        {
          "propertyId": "66040334-7e19-4b0b-545f-b176193e1bec",
          "propertyName": "Location",
          "modelPropertyName": null,
          "isKey": false,
          "isReadOnly": false,
          "isRequired": false,
          "defaultValue": null,
          "referencingEntityKey": null,
          "relatedModelPropertyName": null
        },
        {
          "propertyId": "7243dd6a-960a-6047-1040-4194c44fe05b",
          "propertyName": "Latitude",
          "modelPropertyName": null,
          "isKey": false,
          "isReadOnly": false,
          "isRequired": false,
          "defaultValue": null,
          "referencingEntityKey": null,
          "relatedModelPropertyName": null
        },
        {
          "propertyId": "915ab9fe-8432-1339-87a7-c67cb8773596",
          "propertyName": "Longitude",
          "modelPropertyName": null,
          "isKey": false,
          "isReadOnly": false,
          "isRequired": false,
          "defaultValue": null,
          "referencingEntityKey": null,
          "relatedModelPropertyName": null
        },
        {
          "propertyId": "4794f178-9399-f432-badd-b8189fe93a07",
          "propertyName": "TimeFrom",
          "modelPropertyName": null,
          "isKey": false,
          "isReadOnly": false,
          "isRequired": false,
          "defaultValue": null,
          "referencingEntityKey": null,
          "relatedModelPropertyName": null
        },
        {
          "propertyId": "c4a9ab10-40dd-7535-231e-35d3cf220393",
          "propertyName": "TimeTo",
          "modelPropertyName": null,
          "isKey": false,
          "isReadOnly": false,
          "isRequired": false,
          "defaultValue": null,
          "referencingEntityKey": null,
          "relatedModelPropertyName": null
        },
        {
          "propertyId": "4068ec7b-870c-f7b7-dfee-a42ee850ec23",
          "propertyName": "CreatedAt",
          "modelPropertyName": null,
          "isKey": false,
          "isReadOnly": false,
          "isRequired": false,
          "defaultValue": null,
          "referencingEntityKey": null,
          "relatedModelPropertyName": null
        },
        {
          "propertyId": "3c07c985-9cea-f577-99c3-e2ac9161d179",
          "propertyName": "CreatedBy",
          "modelPropertyName": null,
          "isKey": false,
          "isReadOnly": false,
          "isRequired": false,
          "defaultValue": "$user",
          "referencingEntityKey": null,
          "relatedModelPropertyName": null
        },
        {
          "propertyId": "6eb4bbfe-eb53-313c-cd6d-2c032981943c",
          "propertyName": "IsResolved",
          "modelPropertyName": null,
          "isKey": false,
          "isReadOnly": false,
          "isRequired": false,
          "defaultValue": null,
          "referencingEntityKey": null,
          "relatedModelPropertyName": null
        },
        {
          "propertyId": "00000000-0000-0000-0000-000000000000",
          "propertyName": "Id",
          "modelPropertyName": null,
          "isKey": true,
          "isReadOnly": true,
          "isRequired": null,
          "defaultValue": null,
          "referencingEntityKey": null,
          "relatedModelPropertyName": null
        }
      ],
      "entityRoles": [
        {
          "getOne": true,
          "getAll": true,
          "put": true,
          "post": true,
          "delete": true,
          "editFilter": null,
          "viewFilter": null,
          "roleKey": "anonymous"
        },
        {
          "getOne": true,
          "getAll": true,
          "put": true,
          "post": true,
          "delete": true,
          "editFilter": "{\u0022conjunction\u0022:\u0022and\u0022,\u0022comparisons\u0022:[{\u0022operator\u0022:\u0022eq\u0022,\u0022property\u0022:\u0022createdBy\u0022,\u0022filter\u0022:\u0022$user\u0022}],\u0022operator\u0022:\u0022eq\u0022}",
          "viewFilter": null,
          "roleKey": "user"
        },
        {
          "getOne": true,
          "getAll": true,
          "put": true,
          "post": true,
          "delete": true,
          "editFilter": null,
          "viewFilter": null,
          "roleKey": "admin"
        }
      ],
      "entityRelations": []
    },
    {
      "entityKey": "541a2de9-cb23-741a-c8ff-0a73770f0111",
      "tableName": "TaskReservation",
      "objectName": null,
      "controllerName": "task-reservation",
      "softDeleteColumn": null,
      "defaultValue": null,
      "properties": [
        {
          "propertyId": "d0f28d70-58fc-8c74-2e76-4aec2a9d8147",
          "propertyName": "Task",
          "modelPropertyName": null,
          "isKey": false,
          "isReadOnly": false,
          "isRequired": false,
          "defaultValue": null,
          "referencingEntityKey": "f284bf21-df3d-56c7-573c-a3424169917e",
          "relatedModelPropertyName": null
        },
        {
          "propertyId": "4790a87b-ac04-4303-3d50-b64afff8833d",
          "propertyName": "ReservedBy",
          "modelPropertyName": null,
          "isKey": false,
          "isReadOnly": false,
          "isRequired": false,
          "defaultValue": "$user",
          "referencingEntityKey": null,
          "relatedModelPropertyName": null
        },
        {
          "propertyId": "eabad8bf-29ab-b07c-964b-63efaac71765",
          "propertyName": "ReservedAt",
          "modelPropertyName": null,
          "isKey": false,
          "isReadOnly": false,
          "isRequired": false,
          "defaultValue": null,
          "referencingEntityKey": null,
          "relatedModelPropertyName": null
        },
        {
          "propertyId": "c0e1d3ff-900d-0f80-79f8-e0e519f95981",
          "propertyName": "IsCompleted",
          "modelPropertyName": null,
          "isKey": false,
          "isReadOnly": false,
          "isRequired": false,
          "defaultValue": null,
          "referencingEntityKey": null,
          "relatedModelPropertyName": null
        },
        {
          "propertyId": "00000000-0000-0000-0000-000000000000",
          "propertyName": "Id",
          "modelPropertyName": null,
          "isKey": true,
          "isReadOnly": true,
          "isRequired": null,
          "defaultValue": null,
          "referencingEntityKey": null,
          "relatedModelPropertyName": null
        }
      ],
      "entityRoles": [
        {
          "getOne": true,
          "getAll": true,
          "put": true,
          "post": true,
          "delete": true,
          "editFilter": "{\u0022conjunction\u0022:\u0022and\u0022,\u0022comparisons\u0022:[{\u0022operator\u0022:\u0022eq\u0022,\u0022property\u0022:\u0022reservedBy\u0022,\u0022filter\u0022:\u0022$user\u0022}],\u0022operator\u0022:\u0022eq\u0022}",
          "viewFilter": "{\u0022conjunction\u0022:\u0022and\u0022,\u0022comparisons\u0022:[{\u0022operator\u0022:\u0022eq\u0022,\u0022property\u0022:\u0022reservedBy\u0022,\u0022filter\u0022:\u0022$user\u0022}],\u0022operator\u0022:\u0022eq\u0022}",
          "roleKey": "user"
        },
        {
          "getOne": true,
          "getAll": true,
          "put": true,
          "post": true,
          "delete": true,
          "editFilter": null,
          "viewFilter": null,
          "roleKey": "admin"
        }
      ],
      "entityRelations": []
    },
    {
      "entityKey": "49d05cd0-eeef-6113-16b4-c75f00f4b05f",
      "tableName": "UserKarma",
      "objectName": null,
      "controllerName": "user-karma",
      "softDeleteColumn": null,
      "defaultValue": null,
      "properties": [
        {
          "propertyId": "9f66bc7c-6edb-9a5a-93c6-d1fcc4317e64",
          "propertyName": "UserProfile",
          "modelPropertyName": null,
          "isKey": false,
          "isReadOnly": false,
          "isRequired": false,
          "defaultValue": null,
          "referencingEntityKey": "31099994-b3cc-3ade-768f-8de8d1d47fac",
          "relatedModelPropertyName": null
        },
        {
          "propertyId": "e9c8fe59-cf20-417d-104a-5c40fef7d017",
          "propertyName": "TotalCompleted",
          "modelPropertyName": null,
          "isKey": false,
          "isReadOnly": false,
          "isRequired": false,
          "defaultValue": null,
          "referencingEntityKey": null,
          "relatedModelPropertyName": null
        },
        {
          "propertyId": "5d337289-1456-8857-ffb3-0ac064f0a958",
          "propertyName": "LastCompletedAt",
          "modelPropertyName": null,
          "isKey": false,
          "isReadOnly": false,
          "isRequired": false,
          "defaultValue": null,
          "referencingEntityKey": null,
          "relatedModelPropertyName": null
        },
        {
          "propertyId": "00000000-0000-0000-0000-000000000000",
          "propertyName": "Id",
          "modelPropertyName": null,
          "isKey": true,
          "isReadOnly": true,
          "isRequired": null,
          "defaultValue": null,
          "referencingEntityKey": null,
          "relatedModelPropertyName": null
        }
      ],
      "entityRoles": [
        {
          "getOne": true,
          "getAll": true,
          "put": false,
          "post": false,
          "delete": false,
          "editFilter": null,
          "viewFilter": null,
          "roleKey": "user"
        },
        {
          "getOne": true,
          "getAll": true,
          "put": true,
          "post": true,
          "delete": true,
          "editFilter": null,
          "viewFilter": null,
          "roleKey": "admin"
        },
        {
          "getOne": true,
          "getAll": true,
          "put": false,
          "post": false,
          "delete": false,
          "editFilter": null,
          "viewFilter": null,
          "roleKey": "anonymous"
        }
      ],
      "entityRelations": []
    },
    {
      "entityKey": "D388B2CD-DED7-45D8-9423-F4416811B14B",
      "tableName": "_BeGen_Role",
      "objectName": null,
      "controllerName": null,
      "softDeleteColumn": null,
      "defaultValue": null,
      "properties": [
        {
          "propertyId": null,
          "propertyName": "Id",
          "modelPropertyName": null,
          "isKey": true,
          "isReadOnly": true,
          "isRequired": null,
          "defaultValue": null,
          "referencingEntityKey": null,
          "relatedModelPropertyName": null
        },
        {
          "propertyId": null,
          "propertyName": "RoleName",
          "modelPropertyName": null,
          "isKey": false,
          "isReadOnly": null,
          "isRequired": null,
          "defaultValue": null,
          "referencingEntityKey": null,
          "relatedModelPropertyName": null
        }
      ],
      "entityRoles": null,
      "entityRelations": null
    },
    {
      "entityKey": "3C78639B-8991-440E-B80A-CA327D9F2825",
      "tableName": "_BeGen_User",
      "objectName": null,
      "controllerName": null,
      "softDeleteColumn": null,
      "defaultValue": null,
      "properties": [
        {
          "propertyId": null,
          "propertyName": "Id",
          "modelPropertyName": null,
          "isKey": true,
          "isReadOnly": true,
          "isRequired": null,
          "defaultValue": null,
          "referencingEntityKey": null,
          "relatedModelPropertyName": null
        },
        {
          "propertyId": null,
          "propertyName": "Name",
          "modelPropertyName": null,
          "isKey": false,
          "isReadOnly": null,
          "isRequired": null,
          "defaultValue": null,
          "referencingEntityKey": null,
          "relatedModelPropertyName": null
        }
      ],
      "entityRoles": null,
      "entityRelations": [
        {
          "crossTableName": "_BeGen_CROSS_User_Role",
          "entityReferencingColumnName": "UserId",
          "entityPropertyName": "Roles",
          "relatedEntityReferencingColumnName": "RoleId",
          "relatedEntityPropertyName": "Users",
          "validFromColumnName": null,
          "validToColumnName": null,
          "activeColumnName": null,
          "showInEntity": true,
          "showInRelatedEntity": false,
          "relatedEntityKey": "D388B2CD-DED7-45D8-9423-F4416811B14B"
        }
      ]
    }
  ],
  "integrations": null
}